s3uploader_pilais/__init__.py
s3uploader_pilais/s3uploader.py
s3uploader_pilais-0.0.1.dist-info/METADATA
s3uploader_pilais-0.0.1.dist-info/WHEEL
s3uploader_pilais-0.0.1.dist-info/licenses/LICENSE
s3uploader_pilais-0.0.1.dist-info/RECORD
